jinn_ai/__about__.py
jinn_ai/__init__.py
jinn_ai-0.0.1.dist-info/METADATA
jinn_ai-0.0.1.dist-info/WHEEL
jinn_ai-0.0.1.dist-info/licenses/LICENSE.txt
jinn_ai-0.0.1.dist-info/RECORD
