Metadata-Version: 2.3
Name: jinn-ai
Version: 0.0.1
Summary: TBD
Project-URL: Documentation, https://github.com/ZanSara/jinn-ai#readme
Project-URL: Issues, https://github.com/ZanSara/jinn-ai/issues
Project-URL: Source, https://github.com/ZanSara/jinn-ai
Author-email: ZanSara <github@zansara.dev>
License-Expression: MIT
License-File: LICENSE.txt
Classifier: Development Status :: 4 - Beta
Classifier: Programming Language :: Python
Classifier: Programming Language :: Python :: 3.8
Classifier: Programming Language :: Python :: 3.9
Classifier: Programming Language :: Python :: 3.10
Classifier: Programming Language :: Python :: 3.11
Classifier: Programming Language :: Python :: 3.12
Classifier: Programming Language :: Python :: Implementation :: CPython
Classifier: Programming Language :: Python :: Implementation :: PyPy
Requires-Python: >=3.8
